[
    {
        "id": 481,
        "name": "Ibiza Corso Hotel & Spa",
        "hotel_url": "https://www.momondo.com/hotel-search/Ibiza-Corso-Hotel--Spa,Ibiza-p27274-h30969-details",
        "country": "ES",
        "state": null,
        "city": "Ibiza-Island",
        "address": "c/Illa Plana, 07800 Ibiza, Ibiza Island",
        "rating": "8.40",
        "review_count": 3056,
        "stars": 4,
        "description": "Ibiza Corso Hotel & Spa is a luxury hotel located in the exclusive area of Marina Botafoch Harbour. It offers free access to its gym and unique spa with crystal walls. Each stylish, air-conditioned room at the Ibiza Corso has free WiFi, a balcony and a flat-screen TV. There is also a safe, and a private bathroom with bathrobes and slippers. There are 2 restaurants, one with panoramic views and the other one located in the pool area. You will find an outdoor pool and an indoor one at the spa. The spa also has several types of showers, steam baths and an oxygen room. Pach\u00e1 nightclub is 15 minutes\u2019 walk away. Ibiza Airport is 11 km away.",
        "lat": "38.9117381",
        "lon": "1.4511906",
        "spa": 1,
        "fitness_center": 1,
        "pool": 1,
        "parking": "free",
        "wifi": "free",
        "bar": 1,
        "cribs": 0,
        "restaurant": 1,
        "aircondition": 1,
        "airport_shuttle": "possible",
        "washing_and_drier": 0,
        "ev_charging_station": 0,
        "ocean_view": 1,
        "pet_friendly": "no pets",
        "casino": 1,
        "kitchen": 0,
        "water_park": 0,
        "beach_access": "no",
        "golf": 0,
        "adults_only": 0,
        "kids_friendly_buffet": 0,
        "child_pool": 1,
        "playground": 0,
        "increased_accessibility": 1,
        "unit_wheelchair_accessible": 0
    },
    {
        "id": 5237,
        "name": "Hotel Villa Romantic & Spa",
        "hotel_url": "https://www.momondo.com/hotel-search/Hotel-Villa-Romantic--Spa,Paris-p37687-h2417182-details",
        "country": "FR",
        "state": null,
        "city": "Paris",
        "address": "35 Rue Du Banquier, 75013 Paris",
        "rating": "8.90",
        "review_count": 1310,
        "stars": 4,
        "description": "Villa Romantic is located in Paris, 2.2 km from AccorHotels Arena and 3.1 km from Notre Dame Cathedral. Every room has a flat-screen TV and a private bathroom. Free WiFi is provided. You will find a 24-hour front desk at the property. Op\u00e9ra Bastille is 2.3 km from Villa Romantic, while Louvre Museum is 5.5 km from the property. Orly Airport is 13 km away.",
        "lat": "48.834574",
        "lon": "2.3543205",
        "spa": 1,
        "fitness_center": 1,
        "pool": 1,
        "parking": "no",
        "wifi": "free",
        "bar": 1,
        "cribs": 0,
        "restaurant": 0,
        "aircondition": 1,
        "airport_shuttle": "no",
        "washing_and_drier": 0,
        "ev_charging_station": 0,
        "ocean_view": 0,
        "pet_friendly": "no pets",
        "casino": 0,
        "kitchen": 0,
        "water_park": 0,
        "beach_access": "no",
        "golf": 0,
        "adults_only": 0,
        "kids_friendly_buffet": 0,
        "child_pool": 0,
        "playground": 0,
        "increased_accessibility": 1,
        "unit_wheelchair_accessible": 0
    },
    {
        "id": 3066,
        "name": "Cinemovie",
        "hotel_url": "https://www.momondo.com/hotel-search/Cinemovie,Rome-p42802-h9071360-details",
        "country": "IT",
        "state": null,
        "city": "Rome",
        "address": "175 Via Nomentana primo piano Interno 5, 00161 Rome",
        "rating": "8.60",
        "review_count": 303,
        "stars": 0,
        "description": "No description found",
        "lat": "41.9125877",
        "lon": "12.5057244",
        "spa": 0,
        "fitness_center": 0,
        "pool": 1,
        "parking": "free",
        "wifi": "free",
        "bar": 0,
        "cribs": 1,
        "restaurant": 1,
        "aircondition": 1,
        "airport_shuttle": "possible",
        "washing_and_drier": 0,
        "ev_charging_station": 0,
        "ocean_view": 0,
        "pet_friendly": "pets allowed on request",
        "casino": 0,
        "kitchen": 1,
        "water_park": 0,
        "beach_access": "no",
        "golf": 0,
        "adults_only": 0,
        "kids_friendly_buffet": 0,
        "child_pool": 0,
        "playground": 0,
        "increased_accessibility": 0,
        "unit_wheelchair_accessible": 0
    }
]